EMPOL_GUI/Bias.py
EMPOL_GUI/Flat.py
EMPOL_GUI/GUI_merge.py
EMPOL_GUI/GUI_merge_astid.py
EMPOL_GUI/__init__.py
EMPOL_GUI/empol_astrometry.py
EMPOL_GUI/empol_center_finding.py
EMPOL_GUI/empol_photometry.py
EMPOL_GUI/empol_pol.py
EMPOL_GUI/empol_pol_single_obj.py
EMPOL_GUI/extcatalog.py
EMPOL_GUI/recenter.py
EMPOL_GUI/single_obj_stack.py
EMPOL_GUI/single_phot.py
sources/__init__.py
EMPOL_GUI-2.2.8.dist-info/LICENCE
EMPOL_GUI-2.2.8.dist-info/METADATA
EMPOL_GUI-2.2.8.dist-info/WHEEL
EMPOL_GUI-2.2.8.dist-info/top_level.txt
EMPOL_GUI-2.2.8.dist-info/RECORD
