Metadata-Version: 2.1
Name: EMPOL-GUI
Version: 2.2.8
Summary: Astronomial Large Data Reduction GUI - EMPOL
Home-page: https://github.com/aasthagupta128/EMPOL_GUI
Author: Aastha Gupta
Author-email: aastha.gupta1208@gmail.com
Classifier: Programming Language :: Python :: 3
Classifier: License :: OSI Approved :: MIT License
Classifier: Operating System :: OS Independent
License-File: LICENCE
